README.rst
setup.py
selenium_robot/__init__.py
selenium_robot/actions.py
selenium_robot/client.py
selenium_robot/exceptions.py
selenium_robot/models.py
selenium_robot/opts.py
selenium_robot.egg-info/PKG-INFO
selenium_robot.egg-info/SOURCES.txt
selenium_robot.egg-info/dependency_links.txt
selenium_robot.egg-info/requires.txt
selenium_robot.egg-info/top_level.txt