Metadata-Version: 1.1
Name: selenium-robot
Version: 0.0.6
Summary: This is a robot description base selenium.
Home-page: https://pypi.python.org/pypi
Author: Puke
Author-email: 1129090915@qq.com
License: Apache
Platform: UNKNOWN
Classifier: Environment :: Web Environment
Classifier: Intended Audience :: Developers
Classifier: Operating System :: OS Independent
Classifier: Topic :: Text Processing :: Indexing
Classifier: Topic :: Utilities
Classifier: Topic :: Internet
Classifier: Topic :: Software Development :: Libraries :: Python Modules
Classifier: Programming Language :: Python
Classifier: Programming Language :: Python :: 2
Classifier: Programming Language :: Python :: 2.6
Classifier: Programming Language :: Python :: 2.7
